thegreatsuspender.py
the_great_suspender_restore_urls-0.4.dist-info/LICENSE
the_great_suspender_restore_urls-0.4.dist-info/METADATA
the_great_suspender_restore_urls-0.4.dist-info/WHEEL
the_great_suspender_restore_urls-0.4.dist-info/entry_points.txt
the_great_suspender_restore_urls-0.4.dist-info/top_level.txt
the_great_suspender_restore_urls-0.4.dist-info/RECORD
