Metadata-Version: 2.1
Name: the-great-suspender-restore-urls
Version: 0.4
Summary: Restore your thegreatsuspender tabs.
Home-page: http://github.com/barseghyanartur/the-great-suspender-restore-urls
Author: Artur Barseghyan
Author-email: artur.barseghyan@gmail.com
License: GPL-2.0-only OR LGPL-2.1-or-later
Project-URL: Bug Tracker, https://github.com/barseghyanartur/the-great-suspender-restore-urls/issues
Project-URL: Source Code, https://github.com/barseghyanartur/the-great-suspender-restore-urls/
Project-URL: Changelog, https://github.com/barseghyanartur/the-great-suspender-restore-urls/blob/master/CHANGELOG.rst
Keywords: thegreatsuspender,the great suspender
Platform: UNKNOWN
Classifier: Programming Language :: Python
Classifier: Programming Language :: Python :: 3
Classifier: Programming Language :: Python :: 3.6
Classifier: Programming Language :: Python :: 3.7
Classifier: Programming Language :: Python :: 3.8
Classifier: Programming Language :: Python :: 3.9
Classifier: Operating System :: OS Independent
Classifier: Development Status :: 5 - Production/Stable
Classifier: Topic :: Internet
Classifier: License :: OSI Approved :: MIT License
